LICENSE.txt
README.md
regnupg.py
setup.py
regnupg.egg-info/PKG-INFO
regnupg.egg-info/SOURCES.txt
regnupg.egg-info/dependency_links.txt
regnupg.egg-info/top_level.txt